scripts/benchmark.py
scripts/keypoint_rcnn_example.py
scripts/mask_rcnn_example.py
simple_cocotools/__init__.py
simple_cocotools/detections.py
simple_cocotools/evaluator.py
simple_cocotools/utils/__init__.py
simple_cocotools/utils/coco.py
simple_cocotools/utils/data.py
simple_cocotools-1.0.2.dist-info/licenses/LICENSE
simple_cocotools-1.0.2.dist-info/METADATA
simple_cocotools-1.0.2.dist-info/WHEEL
simple_cocotools-1.0.2.dist-info/top_level.txt
simple_cocotools-1.0.2.dist-info/RECORD
