Metadata-Version: 2.4
Name: simple-cocotools
Version: 1.0.2
Summary: simple-cocotools
Home-page: https://github.com/fkodom/simple-cocotools
Author: Frank Odom
Author-email: Frank Odom <frank.odom.iii@gmail.com>
License: MIT
Classifier: Programming Language :: Python :: 3
Requires-Python: >=3.8
License-File: LICENSE
Requires-Dist: numpy<3,>=2.0
Requires-Dist: scipy<2.0,>=1.10.0
Provides-Extra: pycocotools
Requires-Dist: pycocotools~=2.0.10; extra == "pycocotools"
Provides-Extra: test
Requires-Dist: torch==2.7.1; extra == "test"
Requires-Dist: torchvision==0.22.1; extra == "test"
Requires-Dist: tqdm; extra == "test"
Requires-Dist: black==25.1.0; extra == "test"
Requires-Dist: httpx==0.28.1; extra == "test"
Requires-Dist: mypy==1.15.0; extra == "test"
Requires-Dist: pre-commit==4.2.0; extra == "test"
Requires-Dist: pytest==8.3.5; extra == "test"
Requires-Dist: pytest-asyncio==0.26.0; extra == "test"
Requires-Dist: pytest-cov==6.1.1; extra == "test"
Requires-Dist: ruff~=0.11.0; extra == "test"
Requires-Dist: wget~=3.2.0; extra == "test"
Dynamic: author
Dynamic: home-page
Dynamic: license-file
Dynamic: requires-python
